CI_methods_analyser/CI_efficacy.py
CI_methods_analyser/CI_efficacy_diff_betw_two_proportions.py
CI_methods_analyser/CI_efficacy_proportion.py
CI_methods_analyser/__init__.py
CI_methods_analyser/data_functions.py
CI_methods_analyser/math_functions.py
CI_methods_analyser/methods_for_CI_for_diff_betw_two_proportions.py
CI_methods_analyser/methods_for_CI_for_proportion.py
CI_methods_analyser-1.1.0.post1.dist-info/LICENSE
CI_methods_analyser-1.1.0.post1.dist-info/METADATA
CI_methods_analyser-1.1.0.post1.dist-info/WHEEL
CI_methods_analyser-1.1.0.post1.dist-info/top_level.txt
CI_methods_analyser-1.1.0.post1.dist-info/RECORD
