Metadata-Version: 2.1
Name: CI_methods_analyser
Version: 1.1.0.post1
Summary: Analyse efficacy of your own confidence interval (CI) methods
Home-page: https://github.com/Kukuster/CI_methods_analyser
Author: Kukuster
Author-email: KukusterMOP@gmail.com
License: MIT
License-File: LICENSE
Requires-Dist: numpy
Requires-Dist: matplotlib
Requires-Dist: scipy
Requires-Dist: tqdm
